<AnswerKey xmlns="http://mechanicalturk.amazonaws.com/AWSMechanicalTurkDataSchemas/2005-10-01/AnswerKey.xsd">
  <Question>
    <QuestionIdentifier>q_1</QuestionIdentifier>
    <AnswerOption>
      <SelectionIdentifier>aboriginal</SelectionIdentifier>
      <AnswerScore>1</AnswerScore>
    </AnswerOption>
    <AnswerOption>
      <SelectionIdentifier>fiji_acrolectal</SelectionIdentifier>
      <AnswerScore>2</AnswerScore>
    </AnswerOption>
    <AnswerOption>
      <SelectionIdentifier>appalachian</SelectionIdentifier>
      <AnswerScore>3</AnswerScore>
    </AnswerOption>
    <AnswerOption>
      <SelectionIdentifier>australian</SelectionIdentifier>
      <AnswerScore>4</AnswerScore>
    </AnswerOption>
    <AnswerOption>
      <SelectionIdentifier>australian_vernacular</SelectionIdentifier>
      <AnswerScore>5</AnswerScore>
    </AnswerOption>
    <AnswerOption>
      <SelectionIdentifier>bahamian</SelectionIdentifier>
      <AnswerScore>6</AnswerScore>
    </AnswerOption>
    <AnswerOption>
      <SelectionIdentifier>south_african_black</SelectionIdentifier>
      <AnswerScore>7</AnswerScore>
    </AnswerOption>
    <AnswerOption>
      <SelectionIdentifier>cameroon</SelectionIdentifier>
      <AnswerScore>8</AnswerScore>
    </AnswerOption>
    <AnswerOption>
      <SelectionIdentifier>cape_flats</SelectionIdentifier>
      <AnswerScore>9</AnswerScore>
    </AnswerOption>
    <AnswerOption>
      <SelectionIdentifier>channel_islands</SelectionIdentifier>
      <AnswerScore>10</AnswerScore>
    </AnswerOption>
    <AnswerOption>
      <SelectionIdentifier>chicano</SelectionIdentifier>
      <AnswerScore>11</AnswerScore>
    </AnswerOption>
    <AnswerOption>
      <SelectionIdentifier>colloquial_ae</SelectionIdentifier>
      <AnswerScore>12</AnswerScore>
    </AnswerOption>
    <AnswerOption>
      <SelectionIdentifier>singapore</SelectionIdentifier>
      <AnswerScore>13</AnswerScore>
    </AnswerOption>
    <AnswerOption>
      <SelectionIdentifier>aave_earlier</SelectionIdentifier>
      <AnswerScore>14</AnswerScore>
    </AnswerOption>
    <AnswerOption>
      <SelectionIdentifier>east_anglian</SelectionIdentifier>
      <AnswerScore>15</AnswerScore>
    </AnswerOption>
    <AnswerOption>
      <SelectionIdentifier>england_n</SelectionIdentifier>
      <AnswerScore>16</AnswerScore>
    </AnswerOption>
    <AnswerOption>
      <SelectionIdentifier>england_se</SelectionIdentifier>
      <AnswerScore>17</AnswerScore>
    </AnswerOption>
    <AnswerOption>
      <SelectionIdentifier>england_sw</SelectionIdentifier>
      <AnswerScore>18</AnswerScore>
    </AnswerOption>
    <AnswerOption>
      <SelectionIdentifier>falkland_islands</SelectionIdentifier>
      <AnswerScore>19</AnswerScore>
    </AnswerOption>
    <AnswerOption>
      <SelectionIdentifier>ghanaian</SelectionIdentifier>
      <AnswerScore>20</AnswerScore>
    </AnswerOption>
    <AnswerOption>
      <SelectionIdentifier>hk</SelectionIdentifier>
      <AnswerScore>21</AnswerScore>
    </AnswerOption>
    <AnswerOption>
      <SelectionIdentifier>indian</SelectionIdentifier>
      <AnswerScore>22</AnswerScore>
    </AnswerOption>
    <AnswerOption>
      <SelectionIdentifier>indian_south_african</SelectionIdentifier>
      <AnswerScore>23</AnswerScore>
    </AnswerOption>
    <AnswerOption>
      <SelectionIdentifier>irish</SelectionIdentifier>
      <AnswerScore>24</AnswerScore>
    </AnswerOption>
    <AnswerOption>
      <SelectionIdentifier>jamaican</SelectionIdentifier>
      <AnswerScore>25</AnswerScore>
    </AnswerOption>
    <AnswerOption>
      <SelectionIdentifier>kenyan</SelectionIdentifier>
      <AnswerScore>26</AnswerScore>
    </AnswerOption>
    <AnswerOption>
      <SelectionIdentifier>liberian</SelectionIdentifier>
      <AnswerScore>27</AnswerScore>
    </AnswerOption>
    <AnswerOption>
      <SelectionIdentifier>malaysian</SelectionIdentifier>
      <AnswerScore>28</AnswerScore>
    </AnswerOption>
    <AnswerOption>
      <SelectionIdentifier>maltese</SelectionIdentifier>
      <AnswerScore>29</AnswerScore>
    </AnswerOption>
    <AnswerOption>
      <SelectionIdentifier>manx</SelectionIdentifier>
      <AnswerScore>30</AnswerScore>
    </AnswerOption>
    <AnswerOption>
      <SelectionIdentifier>new_zealand</SelectionIdentifier>
      <AnswerScore>31</AnswerScore>
    </AnswerOption>
    <AnswerOption>
      <SelectionIdentifier>newfoundland</SelectionIdentifier>
      <AnswerScore>32</AnswerScore>
    </AnswerOption>
    <AnswerOption>
      <SelectionIdentifier>nigerian</SelectionIdentifier>
      <AnswerScore>33</AnswerScore>
    </AnswerOption>
    <AnswerOption>
      <SelectionIdentifier>orkney</SelectionIdentifier>
      <AnswerScore>34</AnswerScore>
    </AnswerOption>
    <AnswerOption>
      <SelectionIdentifier>ozark</SelectionIdentifier>
      <AnswerScore>35</AnswerScore>
    </AnswerOption>
    <AnswerOption>
      <SelectionIdentifier>pakistani</SelectionIdentifier>
      <AnswerScore>36</AnswerScore>
    </AnswerOption>
    <AnswerOption>
      <SelectionIdentifier>philippine</SelectionIdentifier>
      <AnswerScore>37</AnswerScore>
    </AnswerOption>
    <AnswerOption>
      <SelectionIdentifier>fiji_pure</SelectionIdentifier>
      <AnswerScore>38</AnswerScore>
    </AnswerOption>
    <AnswerOption>
      <SelectionIdentifier>aave_rural</SelectionIdentifier>
      <AnswerScore>39</AnswerScore>
    </AnswerOption>
    <AnswerOption>
      <SelectionIdentifier>scottish</SelectionIdentifier>
      <AnswerScore>40</AnswerScore>
    </AnswerOption>
    <AnswerOption>
      <SelectionIdentifier>se_american_enclave</SelectionIdentifier>
      <AnswerScore>41</AnswerScore>
    </AnswerOption>
    <AnswerOption>
      <SelectionIdentifier>sri_lankan</SelectionIdentifier>
      <AnswerScore>42</AnswerScore>
    </AnswerOption>
    <AnswerOption>
      <SelectionIdentifier>st_helena</SelectionIdentifier>
      <AnswerScore>43</AnswerScore>
    </AnswerOption>
    <AnswerOption>
      <SelectionIdentifier>tanzanian</SelectionIdentifier>
      <AnswerScore>44</AnswerScore>
    </AnswerOption>
    <AnswerOption>
      <SelectionIdentifier>tristan_da_cunha</SelectionIdentifier>
      <AnswerScore>45</AnswerScore>
    </AnswerOption>
    <AnswerOption>
      <SelectionIdentifier>ugandan</SelectionIdentifier>
      <AnswerScore>46</AnswerScore>
    </AnswerOption>
    <AnswerOption>
      <SelectionIdentifier>aave_urban</SelectionIdentifier>
      <AnswerScore>47</AnswerScore>
    </AnswerOption>
    <AnswerOption>
      <SelectionIdentifier>welsh</SelectionIdentifier>
      <AnswerScore>48</AnswerScore>
    </AnswerOption>
    <AnswerOption>
      <SelectionIdentifier>south_african_white</SelectionIdentifier>
      <AnswerScore>49</AnswerScore>
    </AnswerOption>
    <AnswerOption>
      <SelectionIdentifier>zimbabwean_white</SelectionIdentifier>
      <AnswerScore>50</AnswerScore>
    </AnswerOption>
  </Question>

  <Question>
    <QuestionIdentifier>q_2</QuestionIdentifier>

    <AnswerOption>
      <SelectionIdentifier>aboriginal</SelectionIdentifier>
      <AnswerScore>100</AnswerScore>
    </AnswerOption>
    <AnswerOption>
      <SelectionIdentifier>fiji_acrolectal</SelectionIdentifier>
      <AnswerScore>200</AnswerScore>
    </AnswerOption>
    <AnswerOption>
      <SelectionIdentifier>appalachian</SelectionIdentifier>
      <AnswerScore>300</AnswerScore>
    </AnswerOption>
    <AnswerOption>
      <SelectionIdentifier>australian</SelectionIdentifier>
      <AnswerScore>400</AnswerScore>
    </AnswerOption>
    <AnswerOption>
      <SelectionIdentifier>australian_vernacular</SelectionIdentifier>
      <AnswerScore>500</AnswerScore>
    </AnswerOption>
    <AnswerOption>
      <SelectionIdentifier>bahamian</SelectionIdentifier>
      <AnswerScore>600</AnswerScore>
    </AnswerOption>
    <AnswerOption>
      <SelectionIdentifier>south_african_black</SelectionIdentifier>
      <AnswerScore>700</AnswerScore>
    </AnswerOption>
    <AnswerOption>
      <SelectionIdentifier>cameroon</SelectionIdentifier>
      <AnswerScore>800</AnswerScore>
    </AnswerOption>
    <AnswerOption>
      <SelectionIdentifier>cape_flats</SelectionIdentifier>
      <AnswerScore>900</AnswerScore>
    </AnswerOption>
    <AnswerOption>
      <SelectionIdentifier>channel_islands</SelectionIdentifier>
      <AnswerScore>1000</AnswerScore>
    </AnswerOption>
    <AnswerOption>
      <SelectionIdentifier>chicano</SelectionIdentifier>
      <AnswerScore>1100</AnswerScore>
    </AnswerOption>
    <AnswerOption>
      <SelectionIdentifier>colloquial_ae</SelectionIdentifier>
      <AnswerScore>1200</AnswerScore>
    </AnswerOption>
    <AnswerOption>
      <SelectionIdentifier>singapore</SelectionIdentifier>
      <AnswerScore>1300</AnswerScore>
    </AnswerOption>
    <AnswerOption>
      <SelectionIdentifier>aave_earlier</SelectionIdentifier>
      <AnswerScore>1400</AnswerScore>
    </AnswerOption>
    <AnswerOption>
      <SelectionIdentifier>east_anglian</SelectionIdentifier>
      <AnswerScore>1500</AnswerScore>
    </AnswerOption>
    <AnswerOption>
      <SelectionIdentifier>england_n</SelectionIdentifier>
      <AnswerScore>1600</AnswerScore>
    </AnswerOption>
    <AnswerOption>
      <SelectionIdentifier>england_se</SelectionIdentifier>
      <AnswerScore>1700</AnswerScore>
    </AnswerOption>
    <AnswerOption>
      <SelectionIdentifier>england_sw</SelectionIdentifier>
      <AnswerScore>1800</AnswerScore>
    </AnswerOption>
    <AnswerOption>
      <SelectionIdentifier>falkland_islands</SelectionIdentifier>
      <AnswerScore>1900</AnswerScore>
    </AnswerOption>
    <AnswerOption>
      <SelectionIdentifier>ghanaian</SelectionIdentifier>
      <AnswerScore>2000</AnswerScore>
    </AnswerOption>
    <AnswerOption>
      <SelectionIdentifier>hk</SelectionIdentifier>
      <AnswerScore>2100</AnswerScore>
    </AnswerOption>
    <AnswerOption>
      <SelectionIdentifier>indian</SelectionIdentifier>
      <AnswerScore>2200</AnswerScore>
    </AnswerOption>
    <AnswerOption>
      <SelectionIdentifier>indian_south_african</SelectionIdentifier>
      <AnswerScore>2300</AnswerScore>
    </AnswerOption>
    <AnswerOption>
      <SelectionIdentifier>irish</SelectionIdentifier>
      <AnswerScore>2400</AnswerScore>
    </AnswerOption>
    <AnswerOption>
      <SelectionIdentifier>jamaican</SelectionIdentifier>
      <AnswerScore>2500</AnswerScore>
    </AnswerOption>
    <AnswerOption>
      <SelectionIdentifier>kenyan</SelectionIdentifier>
      <AnswerScore>2600</AnswerScore>
    </AnswerOption>
    <AnswerOption>
      <SelectionIdentifier>liberian</SelectionIdentifier>
      <AnswerScore>2700</AnswerScore>
    </AnswerOption>
    <AnswerOption>
      <SelectionIdentifier>malaysian</SelectionIdentifier>
      <AnswerScore>2800</AnswerScore>
    </AnswerOption>
    <AnswerOption>
      <SelectionIdentifier>maltese</SelectionIdentifier>
      <AnswerScore>2900</AnswerScore>
    </AnswerOption>
    <AnswerOption>
      <SelectionIdentifier>manx</SelectionIdentifier>
      <AnswerScore>3000</AnswerScore>
    </AnswerOption>
    <AnswerOption>
      <SelectionIdentifier>new_zealand</SelectionIdentifier>
      <AnswerScore>3100</AnswerScore>
    </AnswerOption>
    <AnswerOption>
      <SelectionIdentifier>newfoundland</SelectionIdentifier>
      <AnswerScore>3200</AnswerScore>
    </AnswerOption>
    <AnswerOption>
      <SelectionIdentifier>nigerian</SelectionIdentifier>
      <AnswerScore>3300</AnswerScore>
    </AnswerOption>
    <AnswerOption>
      <SelectionIdentifier>orkney</SelectionIdentifier>
      <AnswerScore>3400</AnswerScore>
    </AnswerOption>
    <AnswerOption>
      <SelectionIdentifier>ozark</SelectionIdentifier>
      <AnswerScore>3500</AnswerScore>
    </AnswerOption>
    <AnswerOption>
      <SelectionIdentifier>pakistani</SelectionIdentifier>
      <AnswerScore>3600</AnswerScore>
    </AnswerOption>
    <AnswerOption>
      <SelectionIdentifier>philippine</SelectionIdentifier>
      <AnswerScore>3700</AnswerScore>
    </AnswerOption>
    <AnswerOption>
      <SelectionIdentifier>fiji_pure</SelectionIdentifier>
      <AnswerScore>3800</AnswerScore>
    </AnswerOption>
    <AnswerOption>
      <SelectionIdentifier>aave_rural</SelectionIdentifier>
      <AnswerScore>3900</AnswerScore>
    </AnswerOption>
    <AnswerOption>
      <SelectionIdentifier>scottish</SelectionIdentifier>
      <AnswerScore>4000</AnswerScore>
    </AnswerOption>
    <AnswerOption>
      <SelectionIdentifier>se_american_enclave</SelectionIdentifier>
      <AnswerScore>4100</AnswerScore>
    </AnswerOption>
    <AnswerOption>
      <SelectionIdentifier>sri_lankan</SelectionIdentifier>
      <AnswerScore>4200</AnswerScore>
    </AnswerOption>
    <AnswerOption>
      <SelectionIdentifier>st_helena</SelectionIdentifier>
      <AnswerScore>4300</AnswerScore>
    </AnswerOption>
    <AnswerOption>
      <SelectionIdentifier>tanzanian</SelectionIdentifier>
      <AnswerScore>4400</AnswerScore>
    </AnswerOption>
    <AnswerOption>
      <SelectionIdentifier>tristan_da_cunha</SelectionIdentifier>
      <AnswerScore>4500</AnswerScore>
    </AnswerOption>
    <AnswerOption>
      <SelectionIdentifier>ugandan</SelectionIdentifier>
      <AnswerScore>4600</AnswerScore>
    </AnswerOption>
    <AnswerOption>
      <SelectionIdentifier>aave_urban</SelectionIdentifier>
      <AnswerScore>4700</AnswerScore>
    </AnswerOption>
    <AnswerOption>
      <SelectionIdentifier>welsh</SelectionIdentifier>
      <AnswerScore>4800</AnswerScore>
    </AnswerOption>
    <AnswerOption>
      <SelectionIdentifier>south_african_white</SelectionIdentifier>
      <AnswerScore>4900</AnswerScore>
    </AnswerOption>
    <AnswerOption>
      <SelectionIdentifier>zimbabwean_white</SelectionIdentifier>
      <AnswerScore>5000</AnswerScore>
    </AnswerOption>
    <AnswerOption>
      <SelectionIdentifier>other</SelectionIdentifier>
      <AnswerScore>5100</AnswerScore>
    </AnswerOption>
  </Question>

</AnswerKey>
